ocomp/__init__.py
ocomp/oclip_pb2.py
ocomp/oclip_pb2_grpc.py
ocomp/open_interface_client.py
ocomp/open_interface_grpc_client.py
ocomp-0.6.dist-info/DESCRIPTION.rst
ocomp-0.6.dist-info/METADATA
ocomp-0.6.dist-info/RECORD
ocomp-0.6.dist-info/WHEEL
ocomp-0.6.dist-info/metadata.json
ocomp-0.6.dist-info/top_level.txt
