Metadata-Version: 2.0
Name: ocomp
Version: 0.6
Summary: Execute the given command over gRPC in Open Command Platform (ocomp)
Home-page: https://github.com/onap/cli
Author: Kanagaraj Manickam
Author-email: mkr1481@gmail.com
License: UNKNOWN
Platform: UNKNOWN
Classifier: Programming Language :: Python :: 3
Classifier: License :: OSI Approved :: Apache Software License
Classifier: Operating System :: OS Independent
Requires-Dist: grpc (==0.3.post19)
Requires-Dist: grpcio (==1.22.0)
